Mit6858ComputerSystemsSecurityLectureNotes/README.md
Mit6858ComputerSystemsSecurityLectureNotes/__init__.py
Mit6858ComputerSystemsSecurityLectureNotes/__main__.py
Mit6858ComputerSystemsSecurityLectureNotes/file.epub
Mit6858ComputerSystemsSecurityLectureNotes/index.html
Mit6858ComputerSystemsSecurityLectureNotes/css/__init__.py
Mit6858ComputerSystemsSecurityLectureNotes/css/annotations.css
Mit6858ComputerSystemsSecurityLectureNotes/css/main.css
Mit6858ComputerSystemsSecurityLectureNotes/css/normalize.css
Mit6858ComputerSystemsSecurityLectureNotes/css/popup.css
Mit6858ComputerSystemsSecurityLectureNotes/font/__init__.py
Mit6858ComputerSystemsSecurityLectureNotes/font/fontello.eot
Mit6858ComputerSystemsSecurityLectureNotes/font/fontello.svg
Mit6858ComputerSystemsSecurityLectureNotes/font/fontello.ttf
Mit6858ComputerSystemsSecurityLectureNotes/font/fontello.woff
Mit6858ComputerSystemsSecurityLectureNotes/img/__init__.py
Mit6858ComputerSystemsSecurityLectureNotes/img/annotator-glyph-sprite.png
Mit6858ComputerSystemsSecurityLectureNotes/img/annotator-icon-sprite.png
Mit6858ComputerSystemsSecurityLectureNotes/img/apple-touch-icon.png
Mit6858ComputerSystemsSecurityLectureNotes/img/cancelfullscreen.png
Mit6858ComputerSystemsSecurityLectureNotes/img/close.png
Mit6858ComputerSystemsSecurityLectureNotes/img/fullscreen.png
Mit6858ComputerSystemsSecurityLectureNotes/img/loader.gif
Mit6858ComputerSystemsSecurityLectureNotes/img/menu-icon.png
Mit6858ComputerSystemsSecurityLectureNotes/img/save.png
Mit6858ComputerSystemsSecurityLectureNotes/img/saved.png
Mit6858ComputerSystemsSecurityLectureNotes/img/settings-s.png
Mit6858ComputerSystemsSecurityLectureNotes/img/settings.png
Mit6858ComputerSystemsSecurityLectureNotes/img/star.png
Mit6858ComputerSystemsSecurityLectureNotes/js/__init__.py
Mit6858ComputerSystemsSecurityLectureNotes/js/epub.js
Mit6858ComputerSystemsSecurityLectureNotes/js/epub.min.js
Mit6858ComputerSystemsSecurityLectureNotes/js/epub.min.map
mit_6_858_computer_systems_security_lecture_notes-2024.2.29.0.dist-info/METADATA
mit_6_858_computer_systems_security_lecture_notes-2024.2.29.0.dist-info/WHEEL
mit_6_858_computer_systems_security_lecture_notes-2024.2.29.0.dist-info/entry_points.txt
mit_6_858_computer_systems_security_lecture_notes-2024.2.29.0.dist-info/top_level.txt
mit_6_858_computer_systems_security_lecture_notes-2024.2.29.0.dist-info/RECORD
